Metadata-Version: 2.1
Name: deeppheno
Version: 1.0.0
Summary: DeepPheno phenotype predictor
Home-page: UNKNOWN
Author: Maxat Kulmanov
Author-email: maxat.kulmanov@kaust.edu.sa
License: Apache 2.0
Download-URL: https://github.com/bio-ontology-research-group/deeppheno/archive/v1.0.0.tar.gz
Platform: UNKNOWN
Requires-Python: >=3.6, <3.8
